README.rst
setup.py
fwrite/__init__.py
fwrite/fwrite.py
fwrite.egg-info/PKG-INFO
fwrite.egg-info/SOURCES.txt
fwrite.egg-info/dependency_links.txt
fwrite.egg-info/entry_points.txt
fwrite.egg-info/top_level.txt