Metadata-Version: 1.0
Name: fwrite
Version: 0.1
Summary: create files of the desired size
Home-page: https://github.com/pdrb/fwrite
Author: Pedro Buteri Gonring
Author-email: pedro@bigode.net
License: MIT
Keywords: create file write filewrite fwrite
Platform: UNKNOWN
